review/__init__.py
review/configuration.py
review/get_review_ids.py
review/review.py
review/static/css/review.css
review/static/js/src/review.js
review/templates/no_review.html
review/templates/review.html
review/templates/review_content_problem.html
review/templates/review_content_vertical.html
xblock_review-1.1.5.dist-info/DESCRIPTION.rst
xblock_review-1.1.5.dist-info/METADATA
xblock_review-1.1.5.dist-info/RECORD
xblock_review-1.1.5.dist-info/WHEEL
xblock_review-1.1.5.dist-info/entry_points.txt
xblock_review-1.1.5.dist-info/metadata.json
xblock_review-1.1.5.dist-info/top_level.txt
