Metadata-Version: 2.0
Name: xblock-review
Version: 1.1.5
Summary: The Review XBlock is designed to act as a review tool for learners in their edX course.
Home-page: https://github.com/edx/xblock-review
Author: edX
Author-email: oscm@edx.org
License: AGPL v3
Platform: UNKNOWN
Requires-Dist: XBlock
